Metadata-Version: 2.1
Name: Qmail
Version: 0.0.1
Summary: Sending Mails Made Easy
Author: Akmal Riyas
Author-email: akmalriyas@gmail.com
Keywords: python,mail,email,easymail,gmail,send_mail,otp,passwordgen
License-File: LICENSE.txt
